{
  "version": "1.0.0",
  "restore": {
    "projectUniqueName": "/home/danilokun/Documents/senai/spmedgroup-sprint1-bd-tarde-danilo-j/SPMedicalGroup.WebApi/SPMedicalGroup.WebApi/SPMedicalGroup.WebApi.csproj",
    "projectName": "SPMedicalGroup.WebApi",
    "projectPath": "/home/danilokun/Documents/senai/spmedgroup-sprint1-bd-tarde-danilo-j/SPMedicalGroup.WebApi/SPMedicalGroup.WebApi/SPMedicalGroup.WebApi.csproj",
    "outputPath": "/home/danilokun/Documents/senai/spmedgroup-sprint1-bd-tarde-danilo-j/SPMedicalGroup.WebApi/SPMedicalGroup.WebApi/obj/",
    "projectStyle": "PackageReference",
    "originalTargetFrameworks": [
      "netcoreapp3.1"
    ],
    "sources": {
      "https://api.nuget.org/v3/index.json": {}
    },
    "frameworks": {
      "netcoreapp3.1": {
        "projectReferences": {}
      }
    },
    "warningProperties": {
      "warnAsError": [
        "NU1605"
      ]
    }
  },
  "frameworks": {
    "netcoreapp3.1": {
      "dependencies": {
        "DiscordRichPresence": {
          "target": "Package",
          "version": "[1.0.150, )"
        },
        "Microsoft.AspNetCore.Authentication.JwtBearer": {
          "target": "Package",
          "version": "[2.1.1, )"
        },
        "Microsoft.EntityFrameworkCore.Design": {
          "target": "Package",
          "version": "[2.1.14, )"
        },
        "Microsoft.EntityFrameworkCore.SqlServer": {
          "target": "Package",
          "version": "[2.1.14, )"
        },
        "Microsoft.EntityFrameworkCore.Tools": {
          "include": "Runtime, Build, Native, ContentFiles, Analyzers, BuildTransitive",
          "suppressParent": "All",
          "target": "Package",
          "version": "[2.1.14, )"
        },
        "Microsoft.VisualStudio.Web.CodeGeneration.Design": {
          "target": "Package",
          "version": "[3.1.1, )"
        },
        "Swashbuckle.AspNetCore": {
          "target": "Package",
          "version": "[5.2.1, )"
        },
        "System.IdentityModel.Tokens.Jwt": {
          "target": "Package",
          "version": "[6.5.0, )"
        }
      },
      "imports": [
        "net461",
        "net462",
        "net47",
        "net471",
        "net472",
        "net48"
      ],
      "assetTargetFallback": true,
      "warn": true,
      "frameworkReferences": {
        "Microsoft.AspNetCore.App": {
          "privateAssets": "none"
        },
        "Microsoft.NETCore.App": {
          "privateAssets": "all"
        }
      },
      "runtimeIdentifierGraphPath": "/usr/share/dotnet/sdk/3.1.102/RuntimeIdentifierGraph.json"
    }
  }
}